dynamodb_serialise.py
dynamodb_serialise-1.1.0.dist-info/licenses/LICENSE
dynamodb_serialise-1.1.0.dist-info/METADATA
dynamodb_serialise-1.1.0.dist-info/WHEEL
dynamodb_serialise-1.1.0.dist-info/top_level.txt
dynamodb_serialise-1.1.0.dist-info/RECORD
