Metadata-Version: 2.4
Name: dynamodb-serialise
Version: 1.1.0
Summary: DynamoDB value serialisation and deserialisation
Author-email: Laurie O <laurie_opperman@hotmail.com>
License: MIT
Project-URL: Repository, https://github.com/EpicWink/dynamodb-serialise
Keywords: dynamodb,serialisation
Classifier: Development Status :: 5 - Production/Stable
Classifier: Intended Audience :: Developers
Classifier: License :: OSI Approved :: MIT License
Classifier: Natural Language :: English
Classifier: Operating System :: OS Independent
Classifier: Programming Language :: Python :: 3 :: Only
Classifier: Topic :: Database
Classifier: Topic :: Software Development
Classifier: Typing :: Typed
Requires-Python: ~=3.7
License-File: LICENSE
Dynamic: license-file
